[
  {
    "title": "Introduction",
    "path": "index.md",
    "description": "Overview of the rfw documentation."
  },
  {
    "title": "Getting Started",
    "children": [
      {
        "title": "Introduction",
        "path": "getting-started/introduction.md",
        "description": "Introduction to building with rfw."
      },
      {
        "title": "Quick Start",
        "path": "getting-started/quick-start.md",
        "description": "Minimal steps to run your first rfw app."
      }
    ]
  },
  {
    "title": "Essentials",
    "children": [
      {
        "title": "Creating an Application",
        "path": "essentials/creating-application.md"
      },
      {
        "title": "Template Syntax",
        "path": "essentials/template-syntax.md"
      },
      {
        "title": "Components Basics",
        "path": "essentials/components-basics.md"
      },
      {
        "title": "Reactivity Fundamentals",
        "path": "essentials/reactivity-fundamentals.md"
      },
      {
        "title": "Computed Properties",
        "path": "essentials/computed-properties.md"
      },
      {
        "title": "Class and Style Bindings",
        "path": "essentials/class-and-style-bindings.md"
      },
      {
        "title": "Conditional Rendering",
        "path": "essentials/conditional-rendering.md"
      },
      {
        "title": "List Rendering",
        "path": "essentials/list-rendering.md"
      },
      {
        "title": "Event Handling",
        "path": "essentials/event-handling.md"
      },
      {
        "title": "Signals, Effects & Watchers",
        "path": "essentials/signals-effects-and-effects.md"
      },
      {
        "title": "Template Refs",
        "path": "essentials/template-refs.md"
      },
      {
        "title": "Lifecycle Hooks",
        "path": "essentials/lifecycle-hooks.md"
      }
    ]
  },
  {
    "title": "Architecture",
    "path": "architecture.md"
  },
  {
    "title": "Guide",
    "children": [
      {
        "title": "CLI",
        "path": "guide/cli.md"
      },
      {
        "title": "Why rfw?",
        "path": "guide/features.md"
      },
      {
        "title": "Selective DOM Patching",
        "path": "guide/dom-patching.md"
      },
      {
        "title": "State Management & Suspense",
        "path": "guide/state-management.md"
      },
      {
        "title": "Stores vs signals",
        "path": "guide/store-vs-signals.md"
      },
      {
        "title": "Provide & Inject",
        "path": "guide/provide-inject.md"
      },
      {
        "title": "Routing",
        "path": "guide/router.md"
      },
      {
        "title": "Complex Routing",
        "path": "guide/complex-routing.md"
      },
      {
        "title": "Plugins",
        "path": "guide/plugins.md"
      },
      {
        "title": "Plugin Directives",
        "path": "guide/plugin-directives.md"
      },
      {
        "title": "Assets",
        "path": "guide/assets.md"
      },
      {
        "title": "API Integration",
        "path": "guide/api-integration.md"
      },
      {
        "title": "Scene Graph",
        "path": "guide/scene-graph.md"
      },
      {
        "title": "Cinema",
        "path": "guide/cinema.md"
      },
      {
        "title": "Animations",
        "path": "guide/animation.md"
      },
      {
        "title": "WASM Loader",
        "path": "guide/wasm-loader.md"
      },
      {
        "title": "Manifest",
        "path": "guide/manifest.md"
      },
      {
        "title": "Server Side Computed",
        "path": "guide/ssc.md"
      },
      {
        "title": "Twitch OAuth",
        "path": "guide/twitch-oauth.md"
      },
      {
        "title": "Pathfinding",
        "path": "guide/pathfinding.md"
      },
      {
        "title": "Multiplayer",
        "path": "guide/multiplayer.md"
      }
    ]
  },
  {
    "title": "Plugins",
    "children": [
      {
        "title": "Assets",
        "path": "plugins/assets.md"
      },
      {
        "title": "Bundler",
        "path": "plugins/bundler.md"
      },
      {
        "title": "Copy",
        "path": "plugins/copy.md"
      },
      {
        "title": "Docs",
        "path": "plugins/docs.md"
      },
      {
        "title": "Env",
        "path": "plugins/env.md"
      },
      {
        "title": "Highlight",
        "path": "plugins/highlight.md"
      },
      {
        "title": "i18n",
        "path": "plugins/i18n.md"
      },
      {
        "title": "Pages",
        "path": "plugins/pages.md"
      },
      {
        "title": "Router Analytics",
        "path": "plugins/router-analytics.md"
      },
      {
        "title": "SEO",
        "path": "plugins/seo.md"
      },
      {
        "title": "Tailwind",
        "path": "plugins/tailwind.md"
      },
      {
        "title": "Toast",
        "path": "plugins/toast.md"
      }
    ]
  },
  {
    "title": "Developer Goodies",
    "children": [
      {
        "title": "Devtools",
        "path": "goodies/devtools.md"
      },
      {
        "title": "Debugging",
        "path": "goodies/debugging.md"
      }
    ]
  },
  {
    "title": "API",
    "children": [
      {
        "title": "Overview",
        "path": "api/index.md"
      },
      {
        "title": "core",
        "path": "api/core.md"
      },
      {
        "title": "core component",
        "path": "api/component.md"
      },
      {
        "title": "core error-boundary",
        "path": "api/error-boundary.md"
      },
      {
        "title": "core logger",
        "path": "api/logger.md"
      },
      {
        "title": "core plugin",
        "path": "api/plugin.md"
      },
      {
        "title": "core rtml",
        "path": "api/rtml.md"
      },
      {
        "title": "core suspense",
        "path": "api/suspense.md"
      },
      {
        "title": "composition",
        "path": "api/composition.md"
      },
      {
        "title": "dom",
        "path": "api/dom.md"
      },
      {
        "title": "events",
        "path": "api/events.md"
      },
      {
        "title": "js",
        "path": "api/js.md"
      },
      {
        "title": "markdown",
        "path": "api/markdown.md"
      },
      {
        "title": "http",
        "path": "api/http.md"
      },
      {
        "title": "input",
        "path": "api/input.md"
      },
      {
        "title": "state",
        "path": "api/state.md"
      },
      {
        "title": "signal",
        "path": "api/signal.md"
      },
      {
        "title": "router",
        "path": "api/router.md"
      },
      {
        "title": "host",
        "path": "api/host.md"
      },
      {
        "title": "hostclient",
        "path": "api/hostclient.md"
      },
      {
        "title": "animation",
        "path": "api/animation.md"
      },
      {
        "title": "assets",
        "path": "api/assets.md"
      },
      {
        "title": "cinema",
        "path": "api/cinema.md"
      },
      {
        "title": "devtools",
        "path": "api/devtools.md"
      },
      {
        "title": "math",
        "path": "api/math.md"
      },
      {
        "title": "game loop",
        "path": "api/game-loop.md"
      },
      {
        "title": "scene",
        "path": "api/scene.md"
      },
      {
        "title": "netcode",
        "path": "api/netcode.md"
      },
      {
        "title": "pathfinding",
        "path": "api/pathfinding.md"
      },
      {
        "title": "wasmloader",
        "path": "api/wasmloader.md"
      },
      {
        "title": "shortcut",
        "path": "api/shortcut.md"
      },
      {
        "title": "webgl",
        "path": "api/webgl.md"
      }
    ]
  }
]
